LICENSE
README.md
setup.py
bin/git-dashboard
src/git_dashboard/__init__.py
src/git_dashboard/config.py
src/git_dashboard/dashboard.py
src/git_dashboard/group.py
src/git_dashboard/groups.py
src/git_dashboard.egg-info/PKG-INFO
src/git_dashboard.egg-info/SOURCES.txt
src/git_dashboard.egg-info/dependency_links.txt
src/git_dashboard.egg-info/requires.txt
src/git_dashboard.egg-info/top_level.txt