Metadata-Version: 2.1
Name: git-dashboard
Version: 0.1.15
Summary: Git dashboard
Home-page: https://github.com/kojung/git-dashboard
Author: Jung Ko
Author-email: kojung@gmail.com
License: GPL
Platform: any
Classifier: Programming Language :: Python :: 3
Classifier: License :: OSI Approved :: GNU General Public License (GPL)
Classifier: Operating System :: OS Independent
Requires-Python: >=3.6
License-File: LICENSE
